.gitignore
README.md
setup.py
supervisor_stdout.py
supervisor_stdout.egg-info/PKG-INFO
supervisor_stdout.egg-info/SOURCES.txt
supervisor_stdout.egg-info/dependency_links.txt
supervisor_stdout.egg-info/entry_points.txt
supervisor_stdout.egg-info/top_level.txt