Metadata-Version: 1.0
Name: supervisor-stdout
Version: 0.1.1
Summary: UNKNOWN
Home-page: https://github.com/coderanger/supervisor-stdout
Author: Noah Kantrowitz
Author-email: noah@coderanger.net
License: BSD
Platform: UNKNOWN
Classifier: Development Status :: 1 - Planning
Classifier: Environment :: Web Environment
Classifier: License :: OSI Approved :: BSD License
Classifier: Natural Language :: English
Classifier: Operating System :: OS Independent
Classifier: Programming Language :: Python
